mPyPl/__init__.py
mPyPl/core.py
mPyPl/funcs.py
mPyPl/jsonstream.py
mPyPl/keras.py
mPyPl/mdict.py
mPyPl/multiclass_datastream.py
mPyPl/sink.py
mPyPl/sources.py
mPyPl/video.py
mPyPl/xmlstream.py
mPyPl/utils/__init__.py
mPyPl/utils/coreutils.py
mPyPl/utils/fileutils.py
mPyPl/utils/flowutils.py
mPyPl/utils/image.py
mPyPl/utils/lambdas.py
mPyPl/utils/pipeutils.py
mPyPl/utils/video.py
mPyPl-0.0.3.9.dist-info/LICENSE
mPyPl-0.0.3.9.dist-info/METADATA
mPyPl-0.0.3.9.dist-info/WHEEL
mPyPl-0.0.3.9.dist-info/top_level.txt
mPyPl-0.0.3.9.dist-info/RECORD
