Metadata-Version: 2.1
Name: mPyPl
Version: 0.0.3.9
Summary: Monadic Pipeline Library for Python
Home-page: https://github.com/shwars/mPyPl
Author: Dmitri Soshnikov
Author-email: dmitri@soshnikov.com
License: MIT license
Platform: UNKNOWN
Classifier: Programming Language :: Python :: 3
Classifier: Intended Audience :: Developers
Classifier: License :: OSI Approved :: MIT License
Classifier: Operating System :: OS Independent
Classifier: Topic :: Software Development
Classifier: Topic :: Software Development :: Libraries :: Python Modules
License-File: LICENSE
Requires-Dist: pipe (>=1.5.0)
Requires-Dist: numpy (>=1.11)
Requires-Dist: opencv-python
Requires-Dist: matplotlib
Requires-Dist: keras
